langchain_agentql/__init__.py
langchain_agentql/const.py
langchain_agentql/document_loaders.py
langchain_agentql/llm_descriptions.py
langchain_agentql/load_data.py
langchain_agentql/messages.py
langchain_agentql/py.typed
langchain_agentql/toolkits.py
langchain_agentql/tools/__init__.py
langchain_agentql/tools/extract_web_data_browser_tool.py
langchain_agentql/tools/extract_web_data_tool.py
langchain_agentql/tools/get_web_element_browser_tool.py
langchain_agentql/utils.py
langchain_agentql-1.0.1.dist-info/LICENSE
langchain_agentql-1.0.1.dist-info/METADATA
langchain_agentql-1.0.1.dist-info/WHEEL
langchain_agentql-1.0.1.dist-info/RECORD
