Metadata-Version: 2.3
Name: langchain-agentql
Version: 1.0.1
Summary: An integration package connecting AgentQL and LangChain
License: MIT
Requires-Python: >=3.9,<4.0
Classifier: License :: OSI Approved :: MIT License
Classifier: Programming Language :: Python :: 3
Classifier: Programming Language :: Python :: 3.9
Classifier: Programming Language :: Python :: 3.10
Classifier: Programming Language :: Python :: 3.11
Classifier: Programming Language :: Python :: 3.12
Classifier: Programming Language :: Python :: 3.13
Requires-Dist: agentql (>=1.8.1,<2.0.0)
Requires-Dist: httpx (>=0.28.1,<0.29.0)
Requires-Dist: langchain-community (>=0.3.17,<0.4.0)
Requires-Dist: langchain-core (>=0.3.15,<0.4.0)
Requires-Dist: langchain-openai (>=0.3.4,<0.4.0)
Requires-Dist: langchain-tests (>=0.3.12,<0.4.0)
Requires-Dist: playwright (>=1.50.0,<2.0.0)
Project-URL: Repository, https://github.com/tinyfish-io/agentql-integrations
Project-URL: Source Code, https://github.com/tinyfish-io/agentql-integrations/tree/main/langchain
